dorans/__init__.py
dorans/death.py
dorans/xp.py
dorans/tests/test_death_timer.py
dorans/tests/test_xp.py
dorans-0.2.5.dist-info/METADATA
dorans-0.2.5.dist-info/WHEEL
dorans-0.2.5.dist-info/licenses/LICENSE
dorans-0.2.5.dist-info/RECORD
