Metadata-Version: 2.4
Name: dorans
Version: 0.2.5
Summary: Utilities for the League of Legends Community
License: Attribution-NonCommercial 4.0 International
License-File: LICENSE
Requires-Python: >=3.10
Provides-Extra: test
Requires-Dist: pytest>=2.7.3; extra == 'test'
